json_tabularize/__init__.py
json_tabularize/__main__.py
json_tabularize/tabularize.py
json_tabularize/test.py
json_tabularize-1.0.3.dist-info/LICENSE
json_tabularize-1.0.3.dist-info/METADATA
json_tabularize-1.0.3.dist-info/WHEEL
json_tabularize-1.0.3.dist-info/top_level.txt
json_tabularize-1.0.3.dist-info/RECORD
