Metadata-Version: 2.1
Name: json-tabularize
Version: 1.0.3
Summary: Get deeply nested JSON into tabular format
Home-page: https://github.com/molsonkiko/json_tabularize
Author: Mark Johnston Olson
Author-email: mjolsonsfca@gmail.com
License: MIT/X
Keywords: json
Platform: UNKNOWN
Classifier: Programming Language :: Python
Classifier: Programming Language :: Python :: 3.6
Classifier: Programming Language :: Python :: 3.7
Classifier: Programming Language :: Python :: 3.8
Classifier: Programming Language :: Python :: 3.9
Classifier: Programming Language :: Python :: 3.10
Classifier: Programming Language :: Python :: 3 :: Only
Classifier: Development Status :: 5 - Production/Stable
Classifier: Environment :: Console
Classifier: Intended Audience :: Developers
Classifier: License :: OSI Approved :: MIT License
Requires-Python: >=3.6
License-File: LICENSE
Requires-Dist: genson
